odoo/addons/l10n_fi_banks/README.rst
odoo/addons/l10n_fi_banks/__init__.py
odoo/addons/l10n_fi_banks/__manifest__.py
odoo/addons/l10n_fi_banks/data/res_bank.xml
odoo/addons/l10n_fi_banks/i18n/fi.po
odoo/addons/l10n_fi_banks/i18n/l10n_fi_banks.pot
odoo/addons/l10n_fi_banks/static/description/icon.png
odoo11_addon_l10n_fi_banks-11.0.1.0.0.99.dev1.dist-info/METADATA
odoo11_addon_l10n_fi_banks-11.0.1.0.0.99.dev1.dist-info/RECORD
odoo11_addon_l10n_fi_banks-11.0.1.0.0.99.dev1.dist-info/WHEEL
odoo11_addon_l10n_fi_banks-11.0.1.0.0.99.dev1.dist-info/top_level.txt
